setup.py
bin/slackov
slackov/__init__.py
slackov.egg-info/PKG-INFO
slackov.egg-info/SOURCES.txt
slackov.egg-info/dependency_links.txt
slackov.egg-info/requires.txt
slackov.egg-info/top_level.txt