Metadata-Version: 1.1
Name: slackov
Version: 0.2.1
Summary: A Slack bot that uses Markov chains to learn to        speak like a generic member of your team
Home-page: https://github.com/kneitinger/slackov
Author: Kyle J. Kneitinger
Author-email: kneit@pdx.edu
License: BSD
Platform: UNKNOWN
Classifier: Development Status :: 4 - Beta
Classifier: Environment :: Console
Classifier: Intended Audience :: End Users/Desktop
Classifier: License :: OSI Approved :: BSD License
Classifier: Natural Language :: English
Classifier: Operating System :: OS Independent
Classifier: Topic :: Communications :: Chat
Classifier: Topic :: Text Processing :: Linguistic
